{
    "type": "forge:ore_shapeless",
    "ingredients": [
        {
            "item": "tse:steel_ingot"
        },
		{
            "item": "tse:steel_ingot"
        },
		{
            "item": "tse:steel_ingot"
        },
		{
            "item": "tse:steel_ingot"
        },
		{
            "item": "tse:steel_ingot"
        },
		{
            "item": "tse:steel_ingot"
        },
		{
            "item": "tse:steel_ingot"
        },
		{
            "item": "tse:steel_ingot"
        },
		{
            "item": "tse:steel_ingot"
        }
    ],
    "result": {
        "item": "tse:steel_block"
    }
}
